odoo/addons/purchase_order_supplier_return/README.rst
odoo/addons/purchase_order_supplier_return/__init__.py
odoo/addons/purchase_order_supplier_return/__manifest__.py
odoo/addons/purchase_order_supplier_return/i18n/fr.po
odoo/addons/purchase_order_supplier_return/i18n/hr.po
odoo/addons/purchase_order_supplier_return/i18n/it.po
odoo/addons/purchase_order_supplier_return/i18n/purchase_order_supplier_return.pot
odoo/addons/purchase_order_supplier_return/i18n/sv.po
odoo/addons/purchase_order_supplier_return/models/__init__.py
odoo/addons/purchase_order_supplier_return/models/stock_move.py
odoo/addons/purchase_order_supplier_return/readme/CONTRIBUTORS.md
odoo/addons/purchase_order_supplier_return/readme/DESCRIPTION.md
odoo/addons/purchase_order_supplier_return/readme/USAGE.md
odoo/addons/purchase_order_supplier_return/static/description/icon.png
odoo/addons/purchase_order_supplier_return/static/description/index.html
odoo/addons/purchase_order_supplier_return/tests/__init__.py
odoo/addons/purchase_order_supplier_return/tests/test_purchase_order_supplier_return.py
odoo_addon_purchase_order_supplier_return-18.0.1.0.0.2.dist-info/METADATA
odoo_addon_purchase_order_supplier_return-18.0.1.0.0.2.dist-info/WHEEL
odoo_addon_purchase_order_supplier_return-18.0.1.0.0.2.dist-info/top_level.txt
odoo_addon_purchase_order_supplier_return-18.0.1.0.0.2.dist-info/RECORD
